{
	"name": "ingest_src_stage",
	"properties": {
		"activities": [
			{
				"name": "Copy Source to Stage Data",
				"type": "Copy",
				"dependsOn": [],
				"policy": {
					"timeout": "0.12:00:00",
					"retry": 0,
					"retryIntervalInSeconds": 30,
					"secureOutput": false,
					"secureInput": false
				},
				"userProperties": [],
				"typeProperties": {
					"source": {
						"type": "JsonSource",
						"storeSettings": {
							"type": "AzureBlobFSReadSettings",
							"recursive": true,
							"wildcardFileName": "*.json",
							"enablePartitionDiscovery": false
						},
						"formatSettings": {
							"type": "JsonReadSettings"
						}
					},
					"sink": {
						"type": "JsonSink",
						"storeSettings": {
							"type": "AzureBlobFSWriteSettings"
						},
						"formatSettings": {
							"type": "JsonWriteSettings"
						}
					},
					"enableStaging": false
				},
				"inputs": [
					{
						"referenceName": "DS_Vehicle_Source",
						"type": "DatasetReference",
						"parameters": {
							"folderpath": {
								"value": "@concat(formatDateTime(utcNow(),'yyyy'),'/',formatDateTime(utcNow(),'MM'),'/',formatDateTime(utcNow(),'dd'))",
								"type": "Expression"
							}
						}
					}
				],
				"outputs": [
					{
						"referenceName": "DS_GEVechicle_Landing",
						"type": "DatasetReference",
						"parameters": {
							"landingfolder": "@concat(formatDateTime(utcNow(),'yyyy'),'/',formatDateTime(utcNow(),'MM'),'/',formatDateTime(utcNow(),'dd'),'/')"
						}
					}
				]
			}
		],
		"folder": {
			"name": "GE Vechicle System"
		},
		"annotations": []
	}
}